{
  "date": "2026-06-27",
  "updated_at": "2026-06-27T04:14:04+00:00",
  "source_note": "Chinese hot-topic candidates are collected from public trend pages; English wording is matched to supplied official English headlines when possible, otherwise suggested neutrally.",
  "topics": [
    {
      "rank": 1,
      "chinese_topic": "本周中国多领域解锁硬核成就",
      "platform": "Baidu",
      "heat": "hot",
      "source_url": "https://top.baidu.com/board?tab=realtime",
      "official_english": "China achieves multiple hardcore accomplishments across various fields this week",
      "official_english_source": "Suggested wording",
      "official_english_url": "",
      "why_hot": "Highlights China's recent technological and scientific progress, generating national pride.",
      "share_angle": "Summarize key achievements from the week, focusing on technology and science.",
      "keywords": [
        "China",
        "achievements",
        "technology"
      ]
    },
    {
      "rank": 2,
      "chinese_topic": "男生考703分也烦恼：上北大还是清华",
      "platform": "Baidu",
      "heat": "hot",
      "source_url": "https://top.baidu.com/board?tab=realtime",
      "official_english": "Student scoring 703 in college entrance exam torn between Peking and Tsinghua",
      "official_english_source": "Suggested wording",
      "official_english_url": "",
      "why_hot": "Relatable and aspirational story during college application season.",
      "share_angle": "Discuss the pressure and privilege of top scorers in China's education system.",
      "keywords": [
        "gaokao",
        "Peking University",
        "Tsinghua University"
      ]
    },
    {
      "rank": 3,
      "chinese_topic": "母亲残疾父亲务农 河南女孩高考699分",
      "platform": "Baidu",
      "heat": "hot",
      "source_url": "https://top.baidu.com/board?tab=realtime",
      "official_english": "Henan girl from poor family scores 699 in college entrance exam",
      "official_english_source": "Suggested wording",
      "official_english_url": "",
      "why_hot": "Inspirational story of overcoming adversity through education.",
      "share_angle": "Highlight the role of education in social mobility and the challenges faced by rural students.",
      "keywords": [
        "gaokao",
        "rural education",
        "inspiration"
      ]
    },
    {
      "rank": 4,
      "chinese_topic": "浙大学生畅聊志愿填报并送祝福",
      "platform": "Baidu",
      "heat": "hot",
      "source_url": "https://top.baidu.com/board?tab=realtime",
      "official_english": "Zhejiang University students discuss college application and send blessings",
      "official_english_source": "Suggested wording",
      "official_english_url": "",
      "why_hot": "Timely advice for high school graduates during application season.",
      "share_angle": "Share tips from university students on choosing majors and adjusting to college life.",
      "keywords": [
        "college application",
        "Zhejiang University",
        "advice"
      ]
    },
    {
      "rank": 5,
      "chinese_topic": "“变电站电磁辐射会致癌”不实",
      "platform": "Baidu",
      "heat": "hot",
      "source_url": "https://top.baidu.com/board?tab=realtime",
      "official_english": "Claim that substation electromagnetic radiation causes cancer is false",
      "official_english_source": "Suggested wording",
      "official_english_url": "",
      "why_hot": "Addresses a common public health misconception, relevant to daily life.",
      "share_angle": "Explain the science behind electromagnetic fields and why the claim is unfounded.",
      "keywords": [
        "electromagnetic radiation",
        "myth",
        "public health"
      ]
    },
    {
      "rank": 6,
      "chinese_topic": "天下苦话费贵久矣",
      "platform": "Baidu",
      "heat": "hot",
      "source_url": "https://top.baidu.com/board?tab=realtime",
      "official_english": "Public complains about high telecom fees for a long time",
      "official_english_source": "Suggested wording",
      "official_english_url": "",
      "why_hot": "Widespread consumer dissatisfaction with telecom pricing.",
      "share_angle": "Discuss the debate over telecom fees in China and compare with international rates.",
      "keywords": [
        "telecom fees",
        "consumer rights",
        "China"
      ]
    },
    {
      "rank": 7,
      "chinese_topic": "网民公然侮辱张桂梅校长被行拘",
      "platform": "Baidu",
      "heat": "hot",
      "source_url": "https://top.baidu.com/board?tab=realtime",
      "official_english": "Netizen detained for publicly insulting principal Zhang Guimei",
      "official_english_source": "Suggested wording",
      "official_english_url": "",
      "why_hot": "Involves a revered educator and sparks debate on online speech and respect.",
      "share_angle": "Profile Zhang Guimei's contributions and discuss the legal consequences of online harassment.",
      "keywords": [
        "Zhang Guimei",
        "online insult",
        "detention"
      ]
    },
    {
      "rank": 8,
      "chinese_topic": "网友反馈戒烟后“长出头发”",
      "platform": "Baidu",
      "heat": "hot",
      "source_url": "https://top.baidu.com/board?tab=realtime",
      "official_english": "Netizens report hair regrowth after quitting smoking",
      "official_english_source": "Suggested wording",
      "official_english_url": "",
      "why_hot": "Viral anecdote linking smoking cessation to hair growth, generating curiosity.",
      "share_angle": "Explore the scientific plausibility and encourage healthy habits.",
      "keywords": [
        "smoking cessation",
        "hair growth",
        "health"
      ]
    }
  ]
}
