{
  "date": "2026-06-24",
  "updated_at": "2026-06-24T14:50:36+00:00",
  "source_note": "Chinese hot-topic candidates are collected from public trend pages; English wording is matched to supplied official English headlines when possible, otherwise suggested neutrally.",
  "topics": [
    {
      "rank": 1,
      "chinese_topic": "两册流失海外《永乐大典》终于回家",
      "platform": "Baidu",
      "heat": "hot",
      "source_url": "https://top.baidu.com/board?tab=realtime",
      "official_english": "Two lost volumes of Yongle Encyclopedia return to China",
      "official_english_source": "Suggested wording",
      "official_english_url": "",
      "why_hot": "Cultural relic repatriation resonates with national pride and heritage protection.",
      "share_angle": "Explain the historical significance of the Yongle Encyclopedia and the efforts to recover lost cultural artifacts.",
      "keywords": [
        "Yongle Encyclopedia",
        "cultural repatriation",
        "Chinese heritage"
      ]
    },
    {
      "rank": 2,
      "chinese_topic": "“双一流”高校扩招！投向这些领域",
      "platform": "Baidu",
      "heat": "hot",
      "source_url": "https://top.baidu.com/board?tab=realtime",
      "official_english": "Double First-Class universities expand enrollment in key fields",
      "official_english_source": "Suggested wording",
      "official_english_url": "",
      "why_hot": "Education policy directly affects millions of students and families.",
      "share_angle": "Break down which fields are prioritized and what this means for students and the job market.",
      "keywords": [
        "Double First-Class",
        "university expansion",
        "education policy"
      ]
    },
    {
      "rank": 3,
      "chinese_topic": "河南2026年高考分数线公布",
      "platform": "Baidu",
      "heat": "hot",
      "source_url": "https://top.baidu.com/board?tab=realtime",
      "official_english": "Henan releases 2026 college entrance exam score thresholds",
      "official_english_source": "Suggested wording",
      "official_english_url": "",
      "why_hot": "Annual high-stakes exam results spark widespread discussion.",
      "share_angle": "Compare with previous years and other provinces; explain the gaokao system.",
      "keywords": [
        "gaokao",
        "Henan",
        "college entrance exam"
      ]
    },
    {
      "rank": 4,
      "chinese_topic": "“神秘的东方力量”再现世界杯赛场",
      "platform": "Baidu",
      "heat": "hot",
      "source_url": "https://top.baidu.com/board?tab=realtime",
      "official_english": "Mysterious Eastern power reappears at World Cup",
      "official_english_source": "Suggested wording",
      "official_english_url": "",
      "why_hot": "Combines sports, culture, and curiosity about Chinese traditions.",
      "share_angle": "Explore what 'mysterious Eastern power' refers to (e.g., cupping, acupuncture) and its global reception.",
      "keywords": [
        "World Cup",
        "Chinese traditions",
        "sports culture"
      ]
    },
    {
      "rank": 5,
      "chinese_topic": "亿万年张掖丹霞靠人工染色系谣言",
      "platform": "Baidu",
      "heat": "hot",
      "source_url": "https://top.baidu.com/board?tab=realtime",
      "official_english": "Rumor: Zhangye Danxia landform artificially colored; authorities deny",
      "official_english_source": "Suggested wording",
      "official_english_url": "",
      "why_hot": "Natural wonder preservation and misinformation correction.",
      "share_angle": "Explain the geology of Danxia landforms and how to identify fake news about natural sites.",
      "keywords": [
        "Zhangye Danxia",
        "rumor debunking",
        "geology"
      ]
    },
    {
      "rank": 6,
      "chinese_topic": "卖了500万“神药”出厂价仅几毛钱",
      "platform": "Baidu",
      "heat": "hot",
      "source_url": "https://top.baidu.com/board?tab=realtime",
      "official_english": "Miracle drug sold for 5 million yuan has factory price of just a few jiao",
      "official_english_source": "Suggested wording",
      "official_english_url": "",
      "why_hot": "Exposes healthcare pricing scandals and consumer protection issues.",
      "share_angle": "Discuss the markup chain in pharmaceuticals and regulatory challenges.",
      "keywords": [
        "pharmaceutical pricing",
        "consumer protection",
        "healthcare scandal"
      ]
    },
    {
      "rank": 7,
      "chinese_topic": "中国银行回应逃税23.67亿：推进整改",
      "platform": "Baidu",
      "heat": "hot",
      "source_url": "https://top.baidu.com/board?tab=realtime",
      "official_english": "Bank of China responds to tax evasion allegations of 2.367 billion yuan, pledges rectification",
      "official_english_source": "Suggested wording",
      "official_english_url": "",
      "why_hot": "Major financial institution tax issue raises public concern over corporate accountability.",
      "share_angle": "Explain the tax evasion case and its implications for financial regulation.",
      "keywords": [
        "Bank of China",
        "tax evasion",
        "financial regulation"
      ]
    },
    {
      "rank": 8,
      "chinese_topic": "世界杯正在变成一道数学题",
      "platform": "Baidu",
      "heat": "hot",
      "source_url": "https://top.baidu.com/board?tab=realtime",
      "official_english": "World Cup is turning into a math problem",
      "official_english_source": "Suggested wording",
      "official_english_url": "",
      "why_hot": "Engages sports fans with analytical and statistical angles.",
      "share_angle": "Discuss how data analytics and probability are changing sports strategy and fan engagement.",
      "keywords": [
        "World Cup",
        "data analytics",
        "sports statistics"
      ]
    }
  ]
}
